[{"id":"p16","title":"Victoria Falls","image":{"src":"victoria-falls.jpg","alt":"The powerful cascade of Victoria Falls, a natural wonder between Zambia and Zimbabwe."},"lat":-17.9243,"lon":25.8572},{"id":"p14","title":"Kerala Backwaters","image":{"src":"kerala-backwaters.jpg","alt":"Tranquil waters and lush greenery of the Kerala backwaters."},"lat":9.4981,"lon":76.3388},{"id":"p4","title":"Caribbean Beach","image":{"src":"caribbean-beach.jpg","alt":"Pristine white sand and turquoise waters of a Caribbean beach."},"lat":18.2208,"lon":-66.5901},{"id":"p10","title":"Parisian Streets","image":{"src":"parisian-streets.jpg","alt":"Charming streets of Paris with historic buildings and cafes."},"lat":48.8566,"lon":2.3522}]